littleknow/know_search.py
littleknow/little_know.py
littleknow-1.0.2.dist-info/METADATA
littleknow-1.0.2.dist-info/WHEEL
littleknow-1.0.2.dist-info/RECORD
