Metadata-Version: 2.1
Name: LittleKnow
Version: 1.0.2
Summary: this is a little know base
License: MIT
Author: sf
Requires-Python: >=3.10,<4.0
Classifier: License :: OSI Approved :: MIT License
Classifier: Programming Language :: Python :: 3
Classifier: Programming Language :: Python :: 3.10
Classifier: Programming Language :: Python :: 3.11
Classifier: Programming Language :: Python :: 3.12
Requires-Dist: bs4 (>=0.0.2,<0.0.3)
Requires-Dist: diskcache (>=5.6.3,<6.0.0)
Requires-Dist: gne (>=0.3.1,<0.4.0)
Requires-Dist: haystack-bm25 (>=1.0.2,<2.0.0)
Requires-Dist: jieba (>=0.42.1,<0.43.0)
Requires-Dist: modelscope (>=1.16.1,<2.0.0)
Requires-Dist: shortuuid (>=1.0.13,<2.0.0)
